{
  "name": "Harriet Hicks",
  "age": 56,
  "address": {
    "street": "Iraca Place",
    "city": "Beedioba",
    "state": "NY",
    "zip": "28898"
  },
  "contact": {
    "phone": "(201) 615-6027",
    "servicePhone": "800115697"
  },
  "birthday": "1992-04-02T20:50:49.831Z",
  "ip": "127.97.168.31",
  "foo": "bar",
  "profile": {
    "about": "Zafbilnes dup lur ildebo napos jumda wa wazefad berokgev zaheg sosnud cuhnaul avijab atauc. Roh ralagomul reekurug cenoj ej ejevo onbeto si vulutac gunpumo baenvo koasanil sifufegu zi. Jemamo gebkohar ma ge johoz woaheoc vigakeb gufzilumi ehocvos calimak turev ukatus penihse. Bevo lasli boza vazvazoc oluweeb ja igoohiza he nanoret dir reuvga suphe zu hagto. Usa ze pa si bojcin abogupat le cevhokib vizcipgot nad uma hurhej mo gezfijzag natof. Lin sakicja peki ope utuenki deso bur sojkem veduh giruhmuc iflovfu mozogevit olo lugvi gazod pi.",
    "bio": "Fig pob jecaki sulvi ojde zegrer ozuac ojsenwap ito jansasdu nef mutauko tehtadpep menakni bisze leju. Dubape carow hirmutkef zovjuni zezujoj enanishef hucid dupe obulifef lipli eviidume go ced. Kikofru wemul gak fe cipohme vonodpi hew vu kahkob abtuzi ini heloksuk te ofciz. Po uvibutuso sij gobzawo sahmiega bol cujciv vacli coje goto coem mobod ozaebepa ar cujpavfoz. Kuh kukdehuf guvof tacefhe tiloli mapoj zazmad mi nomcofjo jubgov rumdo gatafo kav."
  },
  "apiKey": "40d2740c3f50aac737394ced5180a527195ed11d9c1df948df06266720e3abd7",
  "currency": {
    "code": "FKP",
    "name": "Falkland Islands (Malvinas) Pound"
  }
}